nonebot_plugin_zyk_novelai/__init__.py
nonebot_plugin_zyk_novelai/config.py
nonebot_plugin_zyk_novelai/work.py
nonebot_plugin_zyk_novelai/resource/novelai_tags.db
nonebot_plugin_zyk_novelai-2.9.5.1.dist-info/LICENSE
nonebot_plugin_zyk_novelai-2.9.5.1.dist-info/METADATA
nonebot_plugin_zyk_novelai-2.9.5.1.dist-info/WHEEL
nonebot_plugin_zyk_novelai-2.9.5.1.dist-info/top_level.txt
nonebot_plugin_zyk_novelai-2.9.5.1.dist-info/RECORD
