Metadata-Version: 2.1
Name: nonebot-plugin-zyk-novelai
Version: 2.9.5.1
Home-page: https://github.com/ZYKsslm/nonebot_plugin_zyk_novelai
Author: ZSSLM
Author-email: 3119964735@qq.com
License: MIT License
License-File: LICENSE
Requires-Dist: fake-useragent
Requires-Dist: httpx
Requires-Dist: colorama
Requires-Dist: Pillow
Requires-Dist: nonebot2
Requires-Dist: nonebot-adapter-onebot
